tpypack/__init__.py
tpypack/example.py
tpypack-0.0.1.dist-info/METADATA
tpypack-0.0.1.dist-info/WHEEL
tpypack-0.0.1.dist-info/top_level.txt
tpypack-0.0.1.dist-info/RECORD
